{"filename": "38457647_011d630cc1_o.jpg", "objects": [{"attributes": [], "names": ["glasses"]}, {"attributes": [], "names": ["shirt"]}, {"attributes": [], "names": ["chair"]}, {"attributes": [], "names": ["table"]}, {"attributes": [], "names": ["rupestral_plant"]}, {"attributes": [], "names": ["denotement"]}, {"attributes": [], "names": ["tailpole"]}, {"attributes": [], "names": ["sky"]}, {"attributes": [], "names": ["non_flowering_plant"]}], "relationships": [{"objects": [3, 8], "relationship": "next to"}, {"objects": [5, 3], "relationship": "next to"}]}